ps_game_21/__init__.py
ps_game_21/cards_info.py
ps_game_21/computer.py
ps_game_21/game_21.py
ps_game_21/game_decision.py
ps_game_21/get_card.py
ps_game_21/player.py
ps_game_21/show.py
ps_game_21-0.0.1.dist-info/METADATA
ps_game_21-0.0.1.dist-info/WHEEL
ps_game_21-0.0.1.dist-info/top_level.txt
ps_game_21-0.0.1.dist-info/RECORD
